{
 "run_id": "baseline-1780177772",
 "status": "running",
 "config": {
  "variant": "baseline",
  "hidden": 64,
  "hidden_layers": 1,
  "epochs": 2,
  "batch_size": 64,
  "lr": 0.001,
  "games": "ALL",
  "only_won": true,
  "max_input_level": null,
  "train_split": "variation",
  "val_split": "non-variant"
 },
 "num_samples": 25381,
 "num_val": 6417,
 "num_params": 27110,
 "steps_total": 794,
 "started_at": 1780177874.1711671,
 "updated_at": 1780178262.2527015,
 "train": [
  {
   "step": 25,
   "datapoints": 1600,
   "epoch": 1,
   "elapsed": 11.9,
   "lr": 0.001,
   "total": 11.79845,
   "action": 1.2787,
   "color": 2.5636,
   "coord": 7.95615
  },
  {
   "step": 50,
   "datapoints": 3200,
   "epoch": 1,
   "elapsed": 19.6,
   "lr": 0.001,
   "total": 10.27165,
   "action": 1.2841,
   "color": 2.10306,
   "coord": 6.88448
  },
  {
   "step": 75,
   "datapoints": 4800,
   "epoch": 1,
   "elapsed": 27.7,
   "lr": 0.001,
   "total": 9.43505,
   "action": 1.13114,
   "color": 2.19002,
   "coord": 6.11388
  },
  {
   "step": 100,
   "datapoints": 6400,
   "epoch": 1,
   "elapsed": 35.8,
   "lr": 0.001,
   "total": 7.62019,
   "action": 0.8897,
   "color": 1.7758,
   "coord": 4.95469
  },
  {
   "step": 125,
   "datapoints": 8000,
   "epoch": 1,
   "elapsed": 44.3,
   "lr": 0.001,
   "total": 6.72628,
   "action": 1.06497,
   "color": 1.38288,
   "coord": 4.27844
  },
  {
   "step": 150,
   "datapoints": 9600,
   "epoch": 1,
   "elapsed": 51.9,
   "lr": 0.001,
   "total": 6.29303,
   "action": 0.86915,
   "color": 1.03241,
   "coord": 4.39147
  },
  {
   "step": 175,
   "datapoints": 11200,
   "epoch": 1,
   "elapsed": 59.2,
   "lr": 0.001,
   "total": 6.46183,
   "action": 0.97672,
   "color": 1.34308,
   "coord": 4.14204
  },
  {
   "step": 200,
   "datapoints": 12800,
   "epoch": 1,
   "elapsed": 66.4,
   "lr": 0.001,
   "total": 6.77291,
   "action": 1.08552,
   "color": 1.20509,
   "coord": 4.4823
  },
  {
   "step": 225,
   "datapoints": 14400,
   "epoch": 1,
   "elapsed": 73.7,
   "lr": 0.001,
   "total": 6.16685,
   "action": 0.88092,
   "color": 1.53258,
   "coord": 3.75336
  },
  {
   "step": 250,
   "datapoints": 16000,
   "epoch": 1,
   "elapsed": 81.4,
   "lr": 0.001,
   "total": 6.5538,
   "action": 1.0408,
   "color": 1.23002,
   "coord": 4.28298
  },
  {
   "step": 275,
   "datapoints": 17600,
   "epoch": 1,
   "elapsed": 89.3,
   "lr": 0.001,
   "total": 5.49442,
   "action": 0.86118,
   "color": 1.03455,
   "coord": 3.59869
  },
  {
   "step": 300,
   "datapoints": 19200,
   "epoch": 1,
   "elapsed": 97.1,
   "lr": 0.001,
   "total": 5.58294,
   "action": 0.76239,
   "color": 1.33143,
   "coord": 3.48912
  },
  {
   "step": 325,
   "datapoints": 20800,
   "epoch": 1,
   "elapsed": 139.0,
   "lr": 0.001,
   "total": 5.65159,
   "action": 0.93686,
   "color": 1.34279,
   "coord": 3.37194
  },
  {
   "step": 350,
   "datapoints": 22400,
   "epoch": 1,
   "elapsed": 146.3,
   "lr": 0.001,
   "total": 4.79397,
   "action": 0.80887,
   "color": 1.09441,
   "coord": 2.89069
  },
  {
   "step": 375,
   "datapoints": 24000,
   "epoch": 1,
   "elapsed": 153.3,
   "lr": 0.001,
   "total": 6.51241,
   "action": 0.98379,
   "color": 1.38137,
   "coord": 4.14724
  },
  {
   "step": 400,
   "datapoints": 25573,
   "epoch": 2,
   "elapsed": 192.7,
   "lr": 0.001,
   "total": 5.7464,
   "action": 0.93566,
   "color": 1.16224,
   "coord": 3.6485
  },
  {
   "step": 425,
   "datapoints": 27173,
   "epoch": 2,
   "elapsed": 201.5,
   "lr": 0.001,
   "total": 5.48671,
   "action": 0.93165,
   "color": 0.92941,
   "coord": 3.62565
  },
  {
   "step": 450,
   "datapoints": 28773,
   "epoch": 2,
   "elapsed": 209.7,
   "lr": 0.001,
   "total": 4.80884,
   "action": 0.92753,
   "color": 0.79358,
   "coord": 3.08773
  },
  {
   "step": 475,
   "datapoints": 30373,
   "epoch": 2,
   "elapsed": 216.8,
   "lr": 0.001,
   "total": 5.10955,
   "action": 0.93206,
   "color": 0.75746,
   "coord": 3.42002
  },
  {
   "step": 500,
   "datapoints": 31973,
   "epoch": 2,
   "elapsed": 224.0,
   "lr": 0.001,
   "total": 5.30065,
   "action": 0.90356,
   "color": 0.97409,
   "coord": 3.423
  },
  {
   "step": 525,
   "datapoints": 33573,
   "epoch": 2,
   "elapsed": 233.0,
   "lr": 0.001,
   "total": 4.32129,
   "action": 0.96649,
   "color": 0.98665,
   "coord": 2.36815
  },
  {
   "step": 550,
   "datapoints": 35173,
   "epoch": 2,
   "elapsed": 243.0,
   "lr": 0.001,
   "total": 5.29257,
   "action": 1.09438,
   "color": 1.12801,
   "coord": 3.07018
  },
  {
   "step": 575,
   "datapoints": 36773,
   "epoch": 2,
   "elapsed": 250.3,
   "lr": 0.001,
   "total": 4.75206,
   "action": 0.98302,
   "color": 1.24734,
   "coord": 2.5217
  },
  {
   "step": 600,
   "datapoints": 38373,
   "epoch": 2,
   "elapsed": 258.8,
   "lr": 0.001,
   "total": 4.71976,
   "action": 0.92399,
   "color": 1.02164,
   "coord": 2.77413
  },
  {
   "step": 625,
   "datapoints": 39973,
   "epoch": 2,
   "elapsed": 298.8,
   "lr": 0.001,
   "total": 4.22856,
   "action": 0.90152,
   "color": 0.92604,
   "coord": 2.401
  },
  {
   "step": 650,
   "datapoints": 41573,
   "epoch": 2,
   "elapsed": 307.3,
   "lr": 0.001,
   "total": 4.3715,
   "action": 0.78931,
   "color": 1.01092,
   "coord": 2.57127
  },
  {
   "step": 675,
   "datapoints": 43173,
   "epoch": 2,
   "elapsed": 315.7,
   "lr": 0.001,
   "total": 5.40028,
   "action": 0.90604,
   "color": 1.03361,
   "coord": 3.46063
  },
  {
   "step": 700,
   "datapoints": 44773,
   "epoch": 2,
   "elapsed": 324.0,
   "lr": 0.001,
   "total": 4.58879,
   "action": 1.01516,
   "color": 0.56568,
   "coord": 3.00795
  },
  {
   "step": 725,
   "datapoints": 46373,
   "epoch": 2,
   "elapsed": 332.5,
   "lr": 0.001,
   "total": 4.9386,
   "action": 1.10652,
   "color": 1.09277,
   "coord": 2.73931
  },
  {
   "step": 750,
   "datapoints": 47973,
   "epoch": 2,
   "elapsed": 341.5,
   "lr": 0.001,
   "total": 4.89382,
   "action": 0.93675,
   "color": 1.3392,
   "coord": 2.61786
  },
  {
   "step": 775,
   "datapoints": 49573,
   "epoch": 2,
   "elapsed": 349.6,
   "lr": 0.001,
   "total": 4.10351,
   "action": 1.02569,
   "color": 0.59058,
   "coord": 2.48724
  },
  {
   "step": 794,
   "datapoints": 50762,
   "epoch": 2,
   "elapsed": 354.9,
   "lr": 0.001,
   "total": 5.25768,
   "action": 1.29014,
   "color": 0.75761,
   "coord": 3.20993
  }
 ],
 "val": [
  {
   "step": 300,
   "datapoints": 19200,
   "total": 5.56802,
   "action": 1.13216,
   "color": 1.336,
   "coord": 3.09986
  },
  {
   "step": 397,
   "datapoints": 25381,
   "total": 5.40162,
   "action": 1.13966,
   "color": 1.32225,
   "coord": 2.93971
  },
  {
   "step": 600,
   "datapoints": 38373,
   "total": 5.24835,
   "action": 1.14669,
   "color": 1.30877,
   "coord": 2.79289
  },
  {
   "step": 794,
   "datapoints": 50762,
   "total": 5.18983,
   "action": 1.13581,
   "color": 1.33087,
   "coord": 2.72315
  }
 ],
 "steps": [
  {
   "step": 25,
   "datapoints": 1600,
   "epoch": 1,
   "elapsed": 11.9,
   "lr": 0.001,
   "total": 11.79845,
   "action": 1.2787,
   "color": 2.5636,
   "coord": 7.95615
  },
  {
   "step": 50,
   "datapoints": 3200,
   "epoch": 1,
   "elapsed": 19.6,
   "lr": 0.001,
   "total": 10.27165,
   "action": 1.2841,
   "color": 2.10306,
   "coord": 6.88448
  },
  {
   "step": 75,
   "datapoints": 4800,
   "epoch": 1,
   "elapsed": 27.7,
   "lr": 0.001,
   "total": 9.43505,
   "action": 1.13114,
   "color": 2.19002,
   "coord": 6.11388
  },
  {
   "step": 100,
   "datapoints": 6400,
   "epoch": 1,
   "elapsed": 35.8,
   "lr": 0.001,
   "total": 7.62019,
   "action": 0.8897,
   "color": 1.7758,
   "coord": 4.95469
  },
  {
   "step": 125,
   "datapoints": 8000,
   "epoch": 1,
   "elapsed": 44.3,
   "lr": 0.001,
   "total": 6.72628,
   "action": 1.06497,
   "color": 1.38288,
   "coord": 4.27844
  },
  {
   "step": 150,
   "datapoints": 9600,
   "epoch": 1,
   "elapsed": 51.9,
   "lr": 0.001,
   "total": 6.29303,
   "action": 0.86915,
   "color": 1.03241,
   "coord": 4.39147
  },
  {
   "step": 175,
   "datapoints": 11200,
   "epoch": 1,
   "elapsed": 59.2,
   "lr": 0.001,
   "total": 6.46183,
   "action": 0.97672,
   "color": 1.34308,
   "coord": 4.14204
  },
  {
   "step": 200,
   "datapoints": 12800,
   "epoch": 1,
   "elapsed": 66.4,
   "lr": 0.001,
   "total": 6.77291,
   "action": 1.08552,
   "color": 1.20509,
   "coord": 4.4823
  },
  {
   "step": 225,
   "datapoints": 14400,
   "epoch": 1,
   "elapsed": 73.7,
   "lr": 0.001,
   "total": 6.16685,
   "action": 0.88092,
   "color": 1.53258,
   "coord": 3.75336
  },
  {
   "step": 250,
   "datapoints": 16000,
   "epoch": 1,
   "elapsed": 81.4,
   "lr": 0.001,
   "total": 6.5538,
   "action": 1.0408,
   "color": 1.23002,
   "coord": 4.28298
  },
  {
   "step": 275,
   "datapoints": 17600,
   "epoch": 1,
   "elapsed": 89.3,
   "lr": 0.001,
   "total": 5.49442,
   "action": 0.86118,
   "color": 1.03455,
   "coord": 3.59869
  },
  {
   "step": 300,
   "datapoints": 19200,
   "epoch": 1,
   "elapsed": 97.1,
   "lr": 0.001,
   "total": 5.58294,
   "action": 0.76239,
   "color": 1.33143,
   "coord": 3.48912
  },
  {
   "step": 325,
   "datapoints": 20800,
   "epoch": 1,
   "elapsed": 139.0,
   "lr": 0.001,
   "total": 5.65159,
   "action": 0.93686,
   "color": 1.34279,
   "coord": 3.37194
  },
  {
   "step": 350,
   "datapoints": 22400,
   "epoch": 1,
   "elapsed": 146.3,
   "lr": 0.001,
   "total": 4.79397,
   "action": 0.80887,
   "color": 1.09441,
   "coord": 2.89069
  },
  {
   "step": 375,
   "datapoints": 24000,
   "epoch": 1,
   "elapsed": 153.3,
   "lr": 0.001,
   "total": 6.51241,
   "action": 0.98379,
   "color": 1.38137,
   "coord": 4.14724
  },
  {
   "step": 400,
   "datapoints": 25573,
   "epoch": 2,
   "elapsed": 192.7,
   "lr": 0.001,
   "total": 5.7464,
   "action": 0.93566,
   "color": 1.16224,
   "coord": 3.6485
  },
  {
   "step": 425,
   "datapoints": 27173,
   "epoch": 2,
   "elapsed": 201.5,
   "lr": 0.001,
   "total": 5.48671,
   "action": 0.93165,
   "color": 0.92941,
   "coord": 3.62565
  },
  {
   "step": 450,
   "datapoints": 28773,
   "epoch": 2,
   "elapsed": 209.7,
   "lr": 0.001,
   "total": 4.80884,
   "action": 0.92753,
   "color": 0.79358,
   "coord": 3.08773
  },
  {
   "step": 475,
   "datapoints": 30373,
   "epoch": 2,
   "elapsed": 216.8,
   "lr": 0.001,
   "total": 5.10955,
   "action": 0.93206,
   "color": 0.75746,
   "coord": 3.42002
  },
  {
   "step": 500,
   "datapoints": 31973,
   "epoch": 2,
   "elapsed": 224.0,
   "lr": 0.001,
   "total": 5.30065,
   "action": 0.90356,
   "color": 0.97409,
   "coord": 3.423
  },
  {
   "step": 525,
   "datapoints": 33573,
   "epoch": 2,
   "elapsed": 233.0,
   "lr": 0.001,
   "total": 4.32129,
   "action": 0.96649,
   "color": 0.98665,
   "coord": 2.36815
  },
  {
   "step": 550,
   "datapoints": 35173,
   "epoch": 2,
   "elapsed": 243.0,
   "lr": 0.001,
   "total": 5.29257,
   "action": 1.09438,
   "color": 1.12801,
   "coord": 3.07018
  },
  {
   "step": 575,
   "datapoints": 36773,
   "epoch": 2,
   "elapsed": 250.3,
   "lr": 0.001,
   "total": 4.75206,
   "action": 0.98302,
   "color": 1.24734,
   "coord": 2.5217
  },
  {
   "step": 600,
   "datapoints": 38373,
   "epoch": 2,
   "elapsed": 258.8,
   "lr": 0.001,
   "total": 4.71976,
   "action": 0.92399,
   "color": 1.02164,
   "coord": 2.77413
  },
  {
   "step": 625,
   "datapoints": 39973,
   "epoch": 2,
   "elapsed": 298.8,
   "lr": 0.001,
   "total": 4.22856,
   "action": 0.90152,
   "color": 0.92604,
   "coord": 2.401
  },
  {
   "step": 650,
   "datapoints": 41573,
   "epoch": 2,
   "elapsed": 307.3,
   "lr": 0.001,
   "total": 4.3715,
   "action": 0.78931,
   "color": 1.01092,
   "coord": 2.57127
  },
  {
   "step": 675,
   "datapoints": 43173,
   "epoch": 2,
   "elapsed": 315.7,
   "lr": 0.001,
   "total": 5.40028,
   "action": 0.90604,
   "color": 1.03361,
   "coord": 3.46063
  },
  {
   "step": 700,
   "datapoints": 44773,
   "epoch": 2,
   "elapsed": 324.0,
   "lr": 0.001,
   "total": 4.58879,
   "action": 1.01516,
   "color": 0.56568,
   "coord": 3.00795
  },
  {
   "step": 725,
   "datapoints": 46373,
   "epoch": 2,
   "elapsed": 332.5,
   "lr": 0.001,
   "total": 4.9386,
   "action": 1.10652,
   "color": 1.09277,
   "coord": 2.73931
  },
  {
   "step": 750,
   "datapoints": 47973,
   "epoch": 2,
   "elapsed": 341.5,
   "lr": 0.001,
   "total": 4.89382,
   "action": 0.93675,
   "color": 1.3392,
   "coord": 2.61786
  },
  {
   "step": 775,
   "datapoints": 49573,
   "epoch": 2,
   "elapsed": 349.6,
   "lr": 0.001,
   "total": 4.10351,
   "action": 1.02569,
   "color": 0.59058,
   "coord": 2.48724
  },
  {
   "step": 794,
   "datapoints": 50762,
   "epoch": 2,
   "elapsed": 354.9,
   "lr": 0.001,
   "total": 5.25768,
   "action": 1.29014,
   "color": 0.75761,
   "coord": 3.20993
  }
 ]
}